Metadata-Version: 2.1
Name: ionsc
Version: 1.1
Summary: A cool cryptography? No? Ok..
Home-page: UNKNOWN
Author: RojanWARE
Author-email: streetyyt@gmail.com
License: MIT License
Keywords: encrypt,decrypt,cryptografy,code,encode,decode,coding
Platform: UNKNOWN
License-File: LICENSE
